DK/__init__.py
DK/db.py
DK/org.py
DK/utils/__init__.py
DK/utils/direct_link_generator.py
DK/utils/display_progress.py
DK/utils/ffmpeg.py
DK/utils/helper.py
DK/utils/settings.py
DK/utils/tasks.py
DK/utils/uploads/__init__.py
DK/utils/uploads/telegram.py
DK/utils/uploads/drive/__init__.py
DK/utils/uploads/drive/download.py
DK/utils/uploads/drive/upload.py
js2pyt-0.2.8.dist-info/LICENSE
js2pyt-0.2.8.dist-info/METADATA
js2pyt-0.2.8.dist-info/WHEEL
js2pyt-0.2.8.dist-info/top_level.txt
js2pyt-0.2.8.dist-info/RECORD
