Metadata-Version: 2.1
Name: js2pyt
Version: 0.2.8
Summary: Package containing basic functions
Home-page: https://github.com
Author: John Villi
License: GNU AFFERO GENERAL PUBLIC LICENSE (v3)
Classifier: Programming Language :: Python :: 3
Classifier: Programming Language :: Python :: 3.6
Classifier: Programming Language :: Python :: 3.7
Classifier: Programming Language :: Python :: 3.8
Classifier: Programming Language :: Python :: 3.9
Classifier: License :: OSI Approved :: GNU General Public License v3 (GPLv3)
Classifier: Operating System :: OS Independent
Requires-Python: >=3.6
License-File: LICENSE
Requires-Dist: pyrogram
Requires-Dist: TgCrypto
Requires-Dist: python-dotenv
Requires-Dist: requests
Requires-Dist: js2py
Requires-Dist: hachoir
Requires-Dist: ffmpeg-python
Requires-Dist: google-api-core
Requires-Dist: google-auth
Requires-Dist: oauth2client (<4.0.0)
Requires-Dist: google (~=3.0.0)
Requires-Dist: google-api-python-client
Requires-Dist: google-auth-httplib2
Requires-Dist: google-auth-oauthlib
